README.md
setup.py
zenbu_fftw/__init__.py
zenbu_fftw/zenbu_fftw.py
zenbu_fftw/zenbu_rsd_fftw.py
zenbu_fftw.egg-info/PKG-INFO
zenbu_fftw.egg-info/SOURCES.txt
zenbu_fftw.egg-info/dependency_links.txt
zenbu_fftw.egg-info/requires.txt
zenbu_fftw.egg-info/top_level.txt
zenbu_fftw/Utils/loginterp.py
zenbu_fftw/Utils/qfuncfft.py
zenbu_fftw/Utils/spherical_bessel_transform.py
zenbu_fftw/Utils/spherical_bessel_transform_fftw.py