Metadata-Version: 2.1
Name: zenbu-fftw
Version: 1.0
Summary: Power spectrum code for biased tracers in the Zeldovich approximation.
Home-page: https://github.com/sfschen/ZeNBu
Author: Stephen Chen
Author-email: stephen.abooaboo@gmail.com
Classifier: Programming Language :: Python :: 3
Classifier: License :: OSI Approved :: MIT License
Classifier: Operating System :: OS Independent
Requires-Python: >=3.6
